py_inspector
