Metadata-Version: 1.1
Name: py-inspector
Version: 0.0.5
Summary: Possibilita a criação de testes para PEP8 e PyLint que serão executados com nose
Home-page: https://github.com/maethorin/py-inspector
Author: Márcio Duarte
Author-email: maethorin@gmail.com
License: MIT
Platform: UNKNOWN
Classifier: Development Status :: 4 - Beta
Classifier: Intended Audience :: Developers
Classifier: License :: OSI Approved :: MIT License
Classifier: Operating System :: OS Independent
Classifier: Programming Language :: Python
Classifier: Programming Language :: Python :: 2.6
Classifier: Programming Language :: Python :: 2.7
Classifier: Topic :: Software Development :: Libraries :: Python Modules
Classifier: Topic :: Internet
